Metadata-Version: 2.1
Name: s3shutil
Version: 0.37
Summary: Easy pythonic API to copy and sync to and from s3
Home-page: https://github.com/andyil/s3shutil
Download-URL: https://github.com/andyil/s3shutil/archive/0.28.tar.gz
License: MIT
Keywords: aws,s3,cloud,storage,shutil,network
Classifier: Development Status :: 4 - Beta
Classifier: Intended Audience :: Developers
Classifier: Intended Audience :: Information Technology
Classifier: Intended Audience :: System Administrators
Classifier: Topic :: Internet
Classifier: License :: OSI Approved :: MIT License
Classifier: Programming Language :: Python :: 3.7
Classifier: Programming Language :: Python :: 3.8
Classifier: Programming Language :: Python :: 3.9
Classifier: Programming Language :: Python :: 3.10
Classifier: Programming Language :: Python :: 3.11
Classifier: Programming Language :: Python :: 3.12
License-File: LICENSE
Requires-Dist: boto3
